{
  "greetings": [
    "안녕하세요",
    "안녕히 계세요",
    "안녕히 가세요",
    "수고하세요",
    "반갑습니다",
    "잘 지냈어요?",
    "감사합니다",
    "괜찮아요"
  ],
  "food": [
    "점심",
    "저녁",
    "아침",
    "밥 먹었어요?",
    "치맥",
    "회식",
    "술자리",
    "맥주",
    "소주",
    "고기집",
    "식당 예약"
  ],
  "office": [
    "회의",
    "보고서",
    "프로젝트",
    "마감일",
    "업무",
    "메일 확인했어요?",
    "팀장님",
    "출근",
    "퇴근",
    "재택근무"
  ],
  "it": [
    "코드",
    "버그",
    "에러",
    "디버그",
    "배포",
    "서버",
    "클라이언트",
    "프론트엔드",
    "백엔드",
    "API",
    "데이터베이스",
    "깃",
    "커밋",
    "푸시",
    "풀",
    "머지",
    "프레임워크",
    "라이브러리",
    "함수",
    "변수",
    "도커",
    "쿠버네티스",
    "클라우드",
    "CI/CD",
    "브랜치",
    "풀 리퀘스트"
  ],
  "social": [
    "생일 축하합니다",
    "파티",
    "초대",
    "선물",
    "케이크",
    "사진 찍자",
    "노래방",
    "게임",
    "영화 보러 가자"
  ],
  "transport": [
    "버스",
    "지하철",
    "택시",
    "비행기",
    "기차",
    "출발",
    "도착",
    "표",
    "예약",
    "길",
    "지도",
    "내비게이션"
  ],
  "shopping": [
    "가게",
    "편의점",
    "마트",
    "쇼핑몰",
    "옷",
    "가격",
    "할인",
    "영수증",
    "현금",
    "카드",
    "계산"
  ]
}
